{
"meta":{"test_sets":["test"],"test_metrics":[{"best_value":"Min","name":"RMSE"}],"learn_metrics":[{"best_value":"Min","name":"RMSE"}],"launch_mode":"Train","parameters":"","iteration_count":20000,"learn_sets":["learn"],"name":"experiment"},
"iterations":[
{"learn":[26.40142152],"iteration":0,"passed_time":0.2613293569,"remaining_time":5226.325808,"test":[26.91972384]},
{"learn":[25.14733286],"iteration":1,"passed_time":0.5592930725,"remaining_time":5592.371432,"test":[26.0495637]},
{"learn":[24.1049509],"iteration":2,"passed_time":0.8328353081,"remaining_time":5551.402552,"test":[25.40890994]},
{"learn":[23.20275311],"iteration":3,"passed_time":1.05088903,"remaining_time":5253.394259,"test":[24.81348947]},
{"learn":[22.22644397],"iteration":4,"passed_time":1.298885499,"remaining_time":5194.243111,"test":[24.12015148]},
{"learn":[21.40808877],"iteration":5,"passed_time":1.472006137,"remaining_time":4905.215118,"test":[23.60212836]},
{"learn":[20.64368594],"iteration":6,"passed_time":1.706468776,"remaining_time":4873.918605,"test":[23.10748485]},
{"learn":[20.02484241],"iteration":7,"passed_time":1.957186093,"remaining_time":4891.008047,"test":[22.69886066]},
{"learn":[19.41149824],"iteration":8,"passed_time":2.217821593,"remaining_time":4926.274608,"test":[22.4348964]},
{"learn":[18.83765898],"iteration":9,"passed_time":2.458178776,"remaining_time":4913.899373,"test":[22.2449861]},
{"learn":[18.29398807],"iteration":10,"passed_time":2.6686666,"remaining_time":4849.452425,"test":[21.90449525]},
{"learn":[17.74906745],"iteration":11,"passed_time":2.965117525,"remaining_time":4938.897425,"test":[21.64417713]},
{"learn":[17.28210839],"iteration":12,"passed_time":3.187514591,"remaining_time":4900.681087,"test":[21.49954946]},
{"learn":[16.86843103],"iteration":13,"passed_time":3.451692282,"remaining_time":4927.537282,"test":[21.32390104]},
{"learn":[16.44065867],"iteration":14,"passed_time":3.705992931,"remaining_time":4937.617915,"test":[21.15459232]},
{"learn":[16.11952579],"iteration":15,"passed_time":3.870876623,"remaining_time":4834.724902,"test":[21.02562461]},
{"learn":[15.77284539],"iteration":16,"passed_time":4.129362694,"remaining_time":4853.944395,"test":[20.88498692]},
{"learn":[15.41029262],"iteration":17,"passed_time":4.367905354,"remaining_time":4848.860266,"test":[20.83852783]},
{"learn":[15.12581264],"iteration":18,"passed_time":4.560687096,"remaining_time":4796.162572,"test":[20.77164991]},
{"learn":[14.86327841],"iteration":19,"passed_time":4.79792717,"remaining_time":4793.129243,"test":[20.69908914]},
{"learn":[14.60981114],"iteration":20,"passed_time":5.013896318,"remaining_time":4770.125455,"test":[20.65001577]},
{"learn":[14.34032423],"iteration":21,"passed_time":5.240973187,"remaining_time":4759.280106,"test":[20.61144362]},
{"learn":[14.11458995],"iteration":22,"passed_time":5.455286362,"remaining_time":4738.271985,"test":[20.54780068]},
{"learn":[13.92862901],"iteration":23,"passed_time":5.652315139,"remaining_time":4704.6103,"test":[20.51689772]},
{"learn":[13.68793026],"iteration":24,"passed_time":5.934807748,"remaining_time":4741.91139,"test":[20.4675094]},
{"learn":[13.46973468],"iteration":25,"passed_time":6.162671646,"remaining_time":4734.353979,"test":[20.41257378]},
{"learn":[13.28985443],"iteration":26,"passed_time":6.347446396,"remaining_time":4695.464699,"test":[20.39565585]},
{"learn":[13.08019822],"iteration":27,"passed_time":6.551119843,"remaining_time":4672.820197,"test":[20.28742227]},
{"learn":[12.85940526],"iteration":28,"passed_time":6.766826928,"remaining_time":4660.010365,"test":[20.26762212]},
{"learn":[12.72777306],"iteration":29,"passed_time":6.9407804,"remaining_time":4620.246153,"test":[20.22696888]},
{"learn":[12.5493025],"iteration":30,"passed_time":7.133445688,"remaining_time":4595.089579,"test":[20.22488682]},
{"learn":[12.35512848],"iteration":31,"passed_time":7.34749352,"remaining_time":4584.835956,"test":[20.2123389]},
{"learn":[12.16676936],"iteration":32,"passed_time":7.53842645,"remaining_time":4561.204877,"test":[20.1528642]},
{"learn":[11.94647468],"iteration":33,"passed_time":7.811041651,"remaining_time":4586.919341,"test":[20.1433792]},
{"learn":[11.77779419],"iteration":34,"passed_time":7.978507355,"remaining_time":4551.168552,"test":[20.06809618]},
{"learn":[11.56259037],"iteration":35,"passed_time":8.307736314,"remaining_time":4607.101327,"test":[20.06432257]},
{"learn":[11.34730332],"iteration":36,"passed_time":8.643614858,"remaining_time":4663.580633,"test":[20.0303217]},
{"learn":[11.14324399],"iteration":37,"passed_time":8.933823109,"remaining_time":4693.078339,"test":[20.01153625]},
{"learn":[11.01947365],"iteration":38,"passed_time":9.107912839,"remaining_time":4661.61662,"test":[19.97946636]},
{"learn":[10.83858764],"iteration":39,"passed_time":9.3874919,"remaining_time":4684.358458,"test":[19.92520043]},
{"learn":[10.68099056],"iteration":40,"passed_time":9.628795334,"remaining_time":4687.344538,"test":[19.8789365]},
{"learn":[10.51455684],"iteration":41,"passed_time":9.879011728,"remaining_time":4694.412287,"test":[19.86233163]},
{"learn":[10.36072655],"iteration":42,"passed_time":10.08164969,"remaining_time":4679.05774,"test":[19.85146215]},
{"learn":[10.18689355],"iteration":43,"passed_time":10.32533809,"remaining_time":4683.010156,"test":[19.84929769]},
{"learn":[10.05623889],"iteration":44,"passed_time":10.52907935,"remaining_time":4669.061743,"test":[19.80708136]},
{"learn":[9.914498626],"iteration":45,"passed_time":10.68838256,"remaining_time":4636.434468,"test":[19.77663386]},
{"learn":[9.761643655],"iteration":46,"passed_time":10.9639952,"remaining_time":4654.565879,"test":[19.73253592]},
{"learn":[9.590114095],"iteration":47,"passed_time":11.16996379,"remaining_time":4642.981614,"test":[19.72372057]},
{"learn":[9.479929079],"iteration":48,"passed_time":11.34354779,"remaining_time":4618.675957,"test":[19.67436061]},
{"learn":[9.332103746],"iteration":49,"passed_time":11.52634087,"remaining_time":4599.010008,"test":[19.63440667]},
{"learn":[9.182486897],"iteration":50,"passed_time":11.76351264,"remaining_time":4601.378698,"test":[19.63862493]},
{"learn":[9.031768515],"iteration":51,"passed_time":11.98869967,"remaining_time":4599.049634,"test":[19.61763696]},
{"learn":[8.823936697],"iteration":52,"passed_time":12.16834753,"remaining_time":4579.660909,"test":[19.52571287]},
{"learn":[8.674121134],"iteration":53,"passed_time":12.40656295,"remaining_time":4582.61675,"test":[19.50628098]},
{"learn":[8.54900857],"iteration":54,"passed_time":12.55244503,"remaining_time":4551.97302,"test":[19.45801854]},
{"learn":[8.342217787],"iteration":55,"passed_time":12.76938057,"remaining_time":4547.72368,"test":[19.44019721]},
{"learn":[8.124881595],"iteration":56,"passed_time":13.0541442,"remaining_time":4567.34733,"test":[19.41032906]},
{"learn":[7.962586109],"iteration":57,"passed_time":13.28332624,"remaining_time":4567.173997,"test":[19.39580871]},
{"learn":[7.828595311],"iteration":58,"passed_time":13.48300185,"remaining_time":4557.0261,"test":[19.38331047]},
{"learn":[7.715893648],"iteration":59,"passed_time":13.67493469,"remaining_time":4544.636629,"test":[19.33641169]},
{"learn":[7.556135733],"iteration":60,"passed_time":13.87588953,"remaining_time":4535.596089,"test":[19.2974153]},
{"learn":[7.342730369],"iteration":61,"passed_time":14.11068356,"remaining_time":4537.722724,"test":[19.23077995]},
{"learn":[7.216100156],"iteration":62,"passed_time":14.30348562,"remaining_time":4526.485599,"test":[19.18745699]},
{"learn":[7.104933523],"iteration":63,"passed_time":14.5471992,"remaining_time":4531.452551,"test":[19.17051887]},
{"learn":[7.009541055],"iteration":64,"passed_time":14.730014,"remaining_time":4517.581986,"test":[19.09917071]},
{"learn":[6.934221451],"iteration":65,"passed_time":14.92475921,"remaining_time":4507.729547,"test":[19.03900859]},
{"learn":[6.801619281],"iteration":66,"passed_time":15.19890792,"remaining_time":4521.788529,"test":[18.99769855]},
{"learn":[6.681969703],"iteration":67,"passed_time":15.40941101,"remaining_time":4516.770298,"test":[18.97426049]},
{"learn":[6.591797087],"iteration":68,"passed_time":15.62635195,"remaining_time":4513.751024,"test":[18.93509448]},
{"learn":[6.474072528],"iteration":69,"passed_time":15.90021411,"remaining_time":4527.018102,"test":[18.93719064]},
{"learn":[6.406319003],"iteration":70,"passed_time":16.07639602,"remaining_time":4512.485863,"test":[18.92864168]},
{"learn":[6.340836222],"iteration":71,"passed_time":16.26660471,"remaining_time":4502.234705,"test":[18.90337339]},
{"learn":[6.246940937],"iteration":72,"passed_time":16.5127916,"remaining_time":4507.539703,"test":[18.88963227]},
{"learn":[6.112805844],"iteration":73,"passed_time":16.71684866,"remaining_time":4501.350356,"test":[18.87786865]},
{"learn":[5.902397656],"iteration":74,"passed_time":17.01890129,"remaining_time":4521.354777,"test":[18.81261566]},
{"learn":[5.849590404],"iteration":75,"passed_time":17.22185484,"remaining_time":4514.845209,"test":[18.79261023]},
{"learn":[5.684029716],"iteration":76,"passed_time":17.50503683,"remaining_time":4529.257775,"test":[18.79121288]},
{"learn":[5.569248023],"iteration":77,"passed_time":17.75696783,"remaining_time":4535.311706,"test":[18.76430342]},
{"learn":[5.431457901],"iteration":78,"passed_time":17.98006599,"remaining_time":4533.935376,"test":[18.75271278]},
{"learn":[5.263131053],"iteration":79,"passed_time":18.29671652,"remaining_time":4555.882414,"test":[18.69202775]},
{"learn":[5.205027037],"iteration":80,"passed_time":18.51856866,"remaining_time":4553.96752,"test":[18.6643852]},
{"learn":[5.145727391],"iteration":81,"passed_time":18.66764506,"remaining_time":4534.416516,"test":[18.65810374]},
{"learn":[5.044739239],"iteration":82,"passed_time":18.77632155,"remaining_time":4505.638509,"test":[18.63834009]},
{"learn":[4.878260181],"iteration":83,"passed_time":18.95339124,"remaining_time":4493.758809,"test":[18.59462115]},
{"learn":[4.786572662],"iteration":84,"passed_time":19.15790489,"remaining_time":4488.584422,"test":[18.60006963]},
{"learn":[4.682377044],"iteration":85,"passed_time":19.35395561,"remaining_time":4481.565953,"test":[18.58261079]},
{"learn":[4.573484351],"iteration":86,"passed_time":19.54811994,"remaining_time":4474.272556,"test":[18.57588457]},
{"learn":[4.446763532],"iteration":87,"passed_time":19.79714648,"remaining_time":4479.554327,"test":[18.53704371]},
{"learn":[4.359201292],"iteration":88,"passed_time":19.99111615,"remaining_time":4472.394536,"test":[18.53263073]},
{"learn":[4.231919577],"iteration":89,"passed_time":20.16123057,"remaining_time":4460.112229,"test":[18.49745926]},
{"learn":[4.143481558],"iteration":90,"passed_time":20.35033583,"remaining_time":4452.250945,"test":[18.47994458]},
{"learn":[4.026487496],"iteration":91,"passed_time":20.60355985,"remaining_time":4458.431191,"test":[18.47476925]},
{"learn":[3.930610251],"iteration":92,"passed_time":21.0002905,"remaining_time":4495.191214,"test":[18.45349869]},
{"learn":[3.883696281],"iteration":93,"passed_time":21.22845931,"remaining_time":4495.465011,"test":[18.44772243]},
{"learn":[3.765748807],"iteration":94,"passed_time":21.59718539,"remaining_time":4525.178687,"test":[18.41841814]},
{"learn":[3.709219801],"iteration":95,"passed_time":21.72508385,"remaining_time":4504.334051,"test":[18.40367412]},
{"learn":[3.636897299],"iteration":96,"passed_time":21.9318106,"remaining_time":4500.090994,"test":[18.40997276]},
{"learn":[3.609532202],"iteration":97,"passed_time":22.07766283,"remaining_time":4483.567813,"test":[18.40053019]},
{"learn":[3.557193918],"iteration":98,"passed_time":22.29789488,"remaining_time":4482.327332,"test":[18.39794472]},
{"learn":[3.483094807],"iteration":99,"passed_time":22.39897022,"remaining_time":4457.395074,"test":[18.3796714]},
{"learn":[3.390670912],"iteration":100,"passed_time":22.73917681,"remaining_time":4480.068112,"test":[18.36716446]},
{"learn":[3.297209658],"iteration":101,"passed_time":23.15541325,"remaining_time":4517.121694,"test":[18.33344778]},
{"learn":[3.242914062],"iteration":102,"passed_time":23.3365805,"remaining_time":4508.038274,"test":[18.32749207]},
{"learn":[3.179783669],"iteration":103,"passed_time":23.5487753,"remaining_time":4505.06186,"test":[18.32286968]},
{"learn":[3.106261972],"iteration":104,"passed_time":23.80290449,"remaining_time":4510.083665,"test":[18.31138811]},
{"learn":[3.02730333],"iteration":105,"passed_time":24.09539324,"remaining_time":4522.205218,"test":[18.31420178]},
{"learn":[2.93684397],"iteration":106,"passed_time":24.3751662,"remaining_time":4531.730665,"test":[18.2966853]},
{"learn":[2.879025515],"iteration":107,"passed_time":24.61925948,"remaining_time":4534.502867,"test":[18.26611314]},
{"learn":[2.867637211],"iteration":108,"passed_time":24.80279454,"remaining_time":4526.16868,"test":[18.26709126]},
{"learn":[2.776005864],"iteration":109,"passed_time":25.16444088,"remaining_time":4550.188446,"test":[18.23347858]},
{"learn":[2.72550605],"iteration":110,"passed_time":25.54466244,"remaining_time":4577.09722,"test":[18.22933116]},
{"learn":[2.645933228],"iteration":111,"passed_time":25.93584317,"remaining_time":4605.464723,"test":[18.22682421]},
{"learn":[2.609953205],"iteration":112,"passed_time":26.06712324,"remaining_time":4587.583008,"test":[18.22210419]},
{"learn":[2.565312883],"iteration":113,"passed_time":26.39310561,"remaining_time":4603.9763,"test":[18.21658371]},
{"learn":[2.53466481],"iteration":114,"passed_time":26.70103034,"remaining_time":4616.95642,"test":[18.197663]},
{"learn":[2.507385028],"iteration":115,"passed_time":26.97216851,"remaining_time":4623.401713,"test":[18.19199597]},
{"learn":[2.49626956],"iteration":116,"passed_time":27.08764458,"remaining_time":4603.27895,"test":[18.18936913]},
{"learn":[2.448878651],"iteration":117,"passed_time":27.28461209,"remaining_time":4597.225911,"test":[18.18244372]},
{"learn":[2.382910682],"iteration":118,"passed_time":27.53253076,"remaining_time":4599.783564,"test":[18.18901182]},
{"learn":[2.341690238],"iteration":119,"passed_time":27.98165335,"remaining_time":4635.627238,"test":[18.17927165]},
{"learn":[2.284215291],"iteration":120,"passed_time":28.31876192,"remaining_time":4652.468332,"test":[18.17532067]},
{"learn":[2.249075497],"iteration":121,"passed_time":28.60928192,"remaining_time":4661.436934,"test":[18.17859419]},
{"learn":[2.205563783],"iteration":122,"passed_time":28.83117337,"remaining_time":4659.164496,"test":[18.17185382]},
{"learn":[2.168511793],"iteration":123,"passed_time":29.18626917,"remaining_time":4678.276501,"test":[18.15379373]},
{"learn":[2.126189497],"iteration":124,"passed_time":29.5240071,"remaining_time":4694.317129,"test":[18.13440169]},
{"learn":[2.071054425],"iteration":125,"passed_time":29.85562427,"remaining_time":4709.132355,"test":[18.12742189]},
{"learn":[2.014703223],"iteration":126,"passed_time":30.2392649,"remaining_time":4731.849696,"test":[18.11974148]},
{"learn":[1.972072044],"iteration":127,"passed_time":30.59192031,"remaining_time":4749.395628,"test":[18.1169984]},
{"learn":[1.924443372],"iteration":128,"passed_time":30.8062901,"remaining_time":4745.362717,"test":[18.10599706]},
{"learn":[1.896612239],"iteration":129,"passed_time":31.10246178,"remaining_time":4753.891658,"test":[18.10235815]},
{"learn":[1.875647658],"iteration":130,"passed_time":31.36128923,"remaining_time":4756.621799,"test":[18.09862053]},
{"learn":[1.855803268],"iteration":131,"passed_time":31.57507152,"remaining_time":4752.526674,"test":[18.10038434]},
{"learn":[1.815470825],"iteration":132,"passed_time":31.90571965,"remaining_time":4765.94686,"test":[18.09420177]},
{"learn":[1.7914602],"iteration":133,"passed_time":32.1123387,"remaining_time":4760.774035,"test":[18.0874309]},
{"learn":[1.752072996],"iteration":134,"passed_time":32.36865505,"remaining_time":4762.987649,"test":[18.08538791]},
{"learn":[1.686312295],"iteration":135,"passed_time":32.66282249,"remaining_time":4770.693426,"test":[18.08523656]},
{"learn":[1.676735511],"iteration":136,"passed_time":32.80602365,"remaining_time":4756.394509,"test":[18.08656562]},
{"learn":[1.620590045],"iteration":137,"passed_time":33.17329447,"remaining_time":4774.550542,"test":[18.0841004]},
{"learn":[1.587040916],"iteration":138,"passed_time":33.5196895,"remaining_time":4789.457217,"test":[18.08702289]},
{"learn":[1.566970811],"iteration":139,"passed_time":33.92733274,"remaining_time":4812.834487,"test":[18.08226951]},
{"learn":[1.524687529],"iteration":140,"passed_time":34.21041827,"remaining_time":4818.33118,"test":[18.08149601]},
{"learn":[1.5020364],"iteration":141,"passed_time":34.41325831,"remaining_time":4812.524531,"test":[18.08017351]},
{"learn":[1.492746614],"iteration":142,"passed_time":34.63033892,"remaining_time":4808.773706,"test":[18.0771585]},
{"learn":[1.478166345],"iteration":143,"passed_time":34.83000306,"remaining_time":4802.670422,"test":[18.07300494]},
{"learn":[1.465114389],"iteration":144,"passed_time":34.97741169,"remaining_time":4789.493166,"test":[18.07410411]},
{"learn":[1.433868874],"iteration":145,"passed_time":35.16096792,"remaining_time":4781.40998,"test":[18.07043618]},
{"learn":[1.410459595],"iteration":146,"passed_time":35.41545207,"remaining_time":4783.013401,"test":[18.066895]},
{"learn":[1.388299041],"iteration":147,"passed_time":35.66548416,"remaining_time":4783.994538,"test":[18.06336861]},
{"learn":[1.35267446],"iteration":148,"passed_time":35.92627268,"remaining_time":4786.392208,"test":[18.06195851]},
{"learn":[1.344542046],"iteration":149,"passed_time":36.10407768,"remaining_time":4777.772947,"test":[18.06076531]},
{"learn":[1.318222771],"iteration":150,"passed_time":36.25663151,"remaining_time":4765.946217,"test":[18.05956409]},
{"learn":[1.293723406],"iteration":151,"passed_time":36.59407021,"remaining_time":4778.415168,"test":[18.05789168]},
{"learn":[1.27199279],"iteration":152,"passed_time":36.95432532,"remaining_time":4793.676436,"test":[18.05940672]},
{"learn":[1.236470691],"iteration":153,"passed_time":37.36363881,"remaining_time":4815.056986,"test":[18.05714854]},
{"learn":[1.212802429],"iteration":154,"passed_time":37.72452745,"remaining_time":4829.956434,"test":[18.05338441]},
{"learn":[1.178613264],"iteration":155,"passed_time":38.03559463,"remaining_time":4838.322691,"test":[18.05197323]},
{"learn":[1.149622772],"iteration":156,"passed_time":38.39445247,"remaining_time":4852.618601,"test":[18.05002776]},
{"learn":[1.12651481],"iteration":157,"passed_time":38.64750655,"remaining_time":4853.44193,"test":[18.04537746]},
{"learn":[1.108840812],"iteration":158,"passed_time":38.96721361,"remaining_time":4862.569089,"test":[18.04509765]},
{"learn":[1.092064162],"iteration":159,"passed_time":39.26444998,"remaining_time":4868.791798,"test":[18.04755223]},
{"learn":[1.0764307],"iteration":160,"passed_time":39.58872554,"remaining_time":4878.265378,"test":[18.04770733]},
{"learn":[1.066734668],"iteration":161,"passed_time":39.76120483,"remaining_time":4869.029515,"test":[18.04993484]},
{"learn":[1.058169142],"iteration":162,"passed_time":39.96156273,"remaining_time":4863.297667,"test":[18.0487525]},
{"learn":[1.029238872],"iteration":163,"passed_time":40.32457109,"remaining_time":4877.30605,"test":[18.04858611]},
{"learn":[0.9999580047],"iteration":164,"passed_time":40.64648119,"remaining_time":4886.199724,"test":[18.04811247]},
{"learn":[0.9779008035],"iteration":165,"passed_time":40.96827102,"remaining_time":4894.967997,"test":[18.04626155]},
{"learn":[0.945312538],"iteration":166,"passed_time":41.39494331,"remaining_time":4916.083297,"test":[18.04987051]},
{"learn":[0.9290413708],"iteration":167,"passed_time":42.13483903,"remaining_time":4973.917426,"test":[18.04870216]},
{"learn":[0.9133024044],"iteration":168,"passed_time":42.64343615,"remaining_time":5003.917055,"test":[18.04727615]},
{"learn":[0.8895872615],"iteration":169,"passed_time":43.10113503,"remaining_time":5027.620633,"test":[18.04351309]},
{"learn":[0.8626587639],"iteration":170,"passed_time":43.52303173,"remaining_time":5046.890036,"test":[18.04347994]},
{"learn":[0.8419930193],"iteration":171,"passed_time":43.80987174,"remaining_time":5050.36126,"test":[18.04134162]},
{"learn":[0.8171468968],"iteration":172,"passed_time":44.22191327,"remaining_time":5068.138002,"test":[18.03765866]},
{"learn":[0.8004241099],"iteration":173,"passed_time":44.53460471,"remaining_time":5074.385477,"test":[18.03582805]},
{"learn":[0.7828507542],"iteration":174,"passed_time":44.84712288,"remaining_time":5080.53835,"test":[18.03417722]},
{"learn":[0.7625701606],"iteration":175,"passed_time":45.28836839,"remaining_time":5101.11713,"test":[18.03486485]},
{"learn":[0.7579677278],"iteration":176,"passed_time":45.50879334,"remaining_time":5096.727743,"test":[18.03456765]},
{"learn":[0.7324419679],"iteration":177,"passed_time":45.98365571,"remaining_time":5120.719233,"test":[18.03374164]},
{"learn":[0.7228304408],"iteration":178,"passed_time":46.26404784,"remaining_time":5122.903309,"test":[18.03315183]},
{"learn":[0.7162021316],"iteration":179,"passed_time":46.43276614,"remaining_time":5112.763472,"test":[18.0318973]},
{"learn":[0.7115010231],"iteration":180,"passed_time":46.75217773,"remaining_time":5119.234311,"test":[18.03145239]},
{"learn":[0.7006122605],"iteration":181,"passed_time":47.15697999,"remaining_time":5134.928733,"test":[18.03064361]},
{"learn":[0.68919614],"iteration":182,"passed_time":47.45514377,"remaining_time":5138.899366,"test":[18.02882858]},
{"learn":[0.6768211877],"iteration":183,"passed_time":47.89392646,"remaining_time":5157.967645,"test":[18.02773019]},
{"learn":[0.6599302416],"iteration":184,"passed_time":48.26278336,"remaining_time":5169.335418,"test":[18.02752179]},
{"learn":[0.6381048857],"iteration":185,"passed_time":48.69713814,"remaining_time":5187.554274,"test":[18.025884]},
{"learn":[0.6256025768],"iteration":186,"passed_time":48.91048937,"remaining_time":5182.157892,"test":[18.0256225]},
{"learn":[0.6216857007],"iteration":187,"passed_time":49.04716076,"remaining_time":5168.735899,"test":[18.02460114]},
{"learn":[0.6075845993],"iteration":188,"passed_time":49.33140546,"remaining_time":5170.92314,"test":[18.02463875]},
{"learn":[0.600161229],"iteration":189,"passed_time":49.50006318,"remaining_time":5161.032903,"test":[18.02409545]},
{"learn":[0.5911611897],"iteration":190,"passed_time":49.69877081,"remaining_time":5154.361,"test":[18.02366124]},
{"learn":[0.5846632168],"iteration":191,"passed_time":49.85969284,"remaining_time":5143.858311,"test":[18.02143746]},
{"learn":[0.5698536073],"iteration":192,"passed_time":50.06801378,"remaining_time":5138.327197,"test":[18.02091611]},
{"learn":[0.5581807397],"iteration":193,"passed_time":50.24406081,"remaining_time":5129.556023,"test":[18.01972198]},
{"learn":[0.552983669],"iteration":194,"passed_time":50.41121374,"remaining_time":5119.969683,"test":[18.01999319]},
{"learn":[0.5438038015],"iteration":195,"passed_time":50.67620057,"remaining_time":5120.364674,"test":[18.01827686]},
{"learn":[0.5347785322],"iteration":196,"passed_time":50.91009288,"remaining_time":5117.627255,"test":[18.01759002]},
{"learn":[0.5240748181],"iteration":197,"passed_time":51.18697991,"remaining_time":5119.215032,"test":[18.01706909]},
{"learn":[0.5109987361],"iteration":198,"passed_time":51.3705996,"remaining_time":5111.503732,"test":[18.01725472]},
{"learn":[0.5037861728],"iteration":199,"passed_time":51.71785548,"remaining_time":5120.067692,"test":[18.01687137]},
{"learn":[0.4991055347],"iteration":200,"passed_time":51.84338139,"remaining_time":5106.70203,"test":[18.01622303]},
{"learn":[0.4860079978],"iteration":201,"passed_time":52.05192052,"remaining_time":5101.603577,"test":[18.01602475]},
{"learn":[0.4788762525],"iteration":202,"passed_time":52.23432153,"remaining_time":5094.004253,"test":[18.01603086]},
{"learn":[0.4745653381],"iteration":203,"passed_time":52.38258471,"remaining_time":5083.164936,"test":[18.01710672]},
{"learn":[0.4669180439],"iteration":204,"passed_time":52.60976415,"remaining_time":5080.050153,"test":[18.01583091]},
{"learn":[0.4606622952],"iteration":205,"passed_time":52.73289648,"remaining_time":5066.965791,"test":[18.01477794]},
{"learn":[0.4482315292],"iteration":206,"passed_time":53.07096981,"remaining_time":5074.558964,"test":[18.01407115]},
{"learn":[0.4369113281],"iteration":207,"passed_time":53.32665925,"remaining_time":5074.23673,"test":[18.01417398]},
{"learn":[0.4320716612],"iteration":208,"passed_time":53.42849276,"remaining_time":5059.345934,"test":[18.01382405]},
{"learn":[0.4207122306],"iteration":209,"passed_time":53.67228919,"remaining_time":5057.9743,"test":[18.01233576]},
{"learn":[0.4140106514],"iteration":210,"passed_time":53.94651335,"remaining_time":5059.467075,"test":[18.01110215]},
{"learn":[0.4059119974],"iteration":211,"passed_time":54.23200092,"remaining_time":5061.994501,"test":[18.01127764]},
{"learn":[0.3979182098],"iteration":212,"passed_time":54.37621902,"remaining_time":5051.372046,"test":[18.01187091]},
{"learn":[0.3907525565],"iteration":213,"passed_time":54.49037914,"remaining_time":5038.068419,"test":[18.01103892]},
{"learn":[0.3801855346],"iteration":214,"passed_time":54.78134119,"remaining_time":5041.157374,"test":[18.00975441]},
{"learn":[0.3729619264],"iteration":215,"passed_time":54.99097067,"remaining_time":5036.765572,"test":[18.00871663]},
{"learn":[0.363903504],"iteration":216,"passed_time":55.2786045,"remaining_time":5039.523654,"test":[18.00705208]},
{"learn":[0.3562005565],"iteration":217,"passed_time":55.55630636,"remaining_time":5041.352534,"test":[18.00794056]},
{"learn":[0.3475632988],"iteration":218,"passed_time":55.72733692,"remaining_time":5033.527177,"test":[18.00529212]},
{"learn":[0.3418975019],"iteration":219,"passed_time":55.8684569,"remaining_time":5023.08217,"test":[18.00416935]},
{"learn":[0.3332669954],"iteration":220,"passed_time":56.09074746,"remaining_time":5019.994996,"test":[18.0045339]},
{"learn":[0.3253077879],"iteration":221,"passed_time":56.32543763,"remaining_time":5018.038313,"test":[18.00348973]},
{"learn":[0.3180461615],"iteration":222,"passed_time":56.53781045,"remaining_time":5014.117835,"test":[18.00315795]},
{"learn":[0.3083215027],"iteration":223,"passed_time":56.89333263,"remaining_time":5022.868509,"test":[18.00198066]},
{"learn":[0.3027712859],"iteration":224,"passed_time":57.13362483,"remaining_time":5021.410804,"test":[18.00171335]},
{"learn":[0.2955766027],"iteration":225,"passed_time":57.38670874,"remaining_time":5021.083091,"test":[18.00166895]},
{"learn":[0.2923788619],"iteration":226,"passed_time":57.51439948,"remaining_time":5009.833572,"test":[18.00129131]},
{"learn":[0.2872919053],"iteration":227,"passed_time":57.72381387,"remaining_time":5005.768631,"test":[18.00081525]},
{"learn":[0.28079037],"iteration":228,"passed_time":57.92477738,"remaining_time":5001.007745,"test":[18.00030929]},
{"learn":[0.27412442],"iteration":229,"passed_time":58.10142143,"remaining_time":4994.196095,"test":[18.00069227]},
{"learn":[0.2694827431],"iteration":230,"passed_time":58.26620478,"remaining_time":4986.42685,"test":[18.00186089]},
{"learn":[0.2641072435],"iteration":231,"passed_time":58.49377748,"remaining_time":4984.073247,"test":[18.00205054]},
{"learn":[0.2621485025],"iteration":232,"passed_time":58.61138938,"remaining_time":4972.409158,"test":[18.00223035]},
{"learn":[0.2586002275],"iteration":233,"passed_time":58.7178111,"remaining_time":4959.898522,"test":[18.00298748]},
{"learn":[0.2542982962],"iteration":234,"passed_time":58.87215314,"remaining_time":4951.523859,"test":[18.00224988]},
{"learn":[0.251676059],"iteration":235,"passed_time":59.03701423,"remaining_time":4944.099785,"test":[18.00207069]},
{"learn":[0.2489961866],"iteration":236,"passed_time":59.1623675,"remaining_time":4933.442485,"test":[18.00126561]},
{"learn":[0.2468196995],"iteration":237,"passed_time":59.30249338,"remaining_time":4924.100311,"test":[18.00142143]},
{"learn":[0.2440187901],"iteration":238,"passed_time":59.48130368,"remaining_time":4918.033648,"test":[18.00156865]},
{"learn":[0.2382829567],"iteration":239,"passed_time":59.77757715,"remaining_time":4921.687185,"test":[18.00145549]},
{"learn":[0.2329943525],"iteration":240,"passed_time":60.03280903,"remaining_time":4921.943044,"test":[18.0006773]},
{"learn":[0.2263998753],"iteration":241,"passed_time":60.17366374,"remaining_time":4912.856398,"test":[18.00096463]},
{"learn":[0.2204291559],"iteration":242,"passed_time":60.44205803,"remaining_time":4914.212924,"test":[17.99998046]},
{"learn":[0.2161820935],"iteration":243,"passed_time":60.66599998,"remaining_time":4911.956949,"test":[18.00035368]},
{"learn":[0.2121246238],"iteration":244,"passed_time":60.86038483,"remaining_time":4907.334296,"test":[17.99982509]},
{"learn":[0.2068740941],"iteration":245,"passed_time":61.0452869,"remaining_time":4901.986168,"test":[17.99947648]},
{"learn":[0.2027217581],"iteration":246,"passed_time":61.22971198,"remaining_time":4896.641703,"test":[17.99910566]},
{"learn":[0.199426407],"iteration":247,"passed_time":61.42983966,"remaining_time":4892.589487,"test":[17.99859102]},
{"learn":[0.1949115632],"iteration":248,"passed_time":61.63079133,"remaining_time":4888.633572,"test":[17.99869854]},
{"learn":[0.1911852383],"iteration":249,"passed_time":61.78763672,"remaining_time":4881.223301,"test":[17.99778677]},
{"learn":[0.1869401382],"iteration":250,"passed_time":61.94294809,"remaining_time":4873.750127,"test":[17.9977451]},
{"learn":[0.1826345269],"iteration":251,"passed_time":62.16821042,"remaining_time":4871.816743,"test":[17.9980084]},
{"learn":[0.1777818086],"iteration":252,"passed_time":62.38791836,"remaining_time":4869.463335,"test":[17.99783505]},
{"learn":[0.1742673502],"iteration":253,"passed_time":62.58075991,"remaining_time":4865.038131,"test":[17.99777168]},
{"learn":[0.171713926],"iteration":254,"passed_time":62.71723975,"remaining_time":4856.281956,"test":[17.99760804]},
{"learn":[0.168349229],"iteration":255,"passed_time":62.89799758,"remaining_time":4851.008063,"test":[17.99699957]},
{"learn":[0.1661613259],"iteration":256,"passed_time":62.99949012,"remaining_time":4839.684566,"test":[17.99668278]},
{"learn":[0.1635051663],"iteration":257,"passed_time":63.1559156,"remaining_time":4832.651496,"test":[17.99679466]},
{"learn":[0.1592033197],"iteration":258,"passed_time":63.378286,"remaining_time":4830.697853,"test":[17.99637379]},
{"learn":[0.1572034127],"iteration":259,"passed_time":63.53352175,"remaining_time":4823.660459,"test":[17.99579182]},
{"learn":[0.1549213964],"iteration":260,"passed_time":63.70580388,"remaining_time":4817.964992,"test":[17.99544576]},
{"learn":[0.153183869],"iteration":261,"passed_time":63.85812604,"remaining_time":4810.807984,"test":[17.99573996]},
{"learn":[0.1507519651],"iteration":262,"passed_time":64.05601015,"remaining_time":4807.123469,"test":[17.99494369]},
{"learn":[0.1487599949],"iteration":263,"passed_time":64.23887747,"remaining_time":4802.342749,"test":[17.99509012]},
{"learn":[0.1468848323],"iteration":264,"passed_time":64.36265756,"remaining_time":4793.196404,"test":[17.99503367]},
{"learn":[0.1447193831],"iteration":265,"passed_time":64.51086665,"remaining_time":4785.930235,"test":[17.99491448]},
{"learn":[0.1411824001],"iteration":266,"passed_time":64.78658035,"remaining_time":4788.140787,"test":[17.9949048]},
{"learn":[0.1386540499],"iteration":267,"passed_time":64.90607374,"remaining_time":4778.830772,"test":[17.99474173]},
{"learn":[0.1347693479],"iteration":268,"passed_time":65.12760155,"remaining_time":4777.073257,"test":[17.99453529]},
{"learn":[0.1333493461],"iteration":269,"passed_time":65.22505387,"remaining_time":4766.260418,"test":[17.9943354]},
{"learn":[0.1318731257],"iteration":270,"passed_time":65.32715986,"remaining_time":4755.86545,"test":[17.99403287]},
{"learn":[0.1306747551],"iteration":271,"passed_time":65.45662601,"remaining_time":4747.53058,"test":[17.99394873]},
{"learn":[0.1289953357],"iteration":272,"passed_time":65.5973595,"remaining_time":4740.070003,"test":[17.99393863]},
{"learn":[0.1258365796],"iteration":273,"passed_time":65.81835503,"remaining_time":4738.441136,"test":[17.99403923]},
{"learn":[0.1244217975],"iteration":274,"passed_time":65.94232388,"remaining_time":4729.86305,"test":[17.99361884]},
{"learn":[0.1228966464],"iteration":275,"passed_time":66.0817492,"remaining_time":4722.450801,"test":[17.99352663]},
{"learn":[0.1198832994],"iteration":276,"passed_time":66.38980716,"remaining_time":4727.098074,"test":[17.99328708]},
{"learn":[0.1168517622],"iteration":277,"passed_time":66.68649177,"remaining_time":4730.902844,"test":[17.99256571]},
{"learn":[0.1137195349],"iteration":278,"passed_time":66.98422929,"remaining_time":4734.752637,"test":[17.99239875]},
{"learn":[0.1115523501],"iteration":279,"passed_time":67.11958987,"remaining_time":4727.136829,"test":[17.99227592]},
{"learn":[0.1095772127],"iteration":280,"passed_time":67.25490717,"remaining_time":4719.571226,"test":[17.99213518]},
{"learn":[0.1072841058],"iteration":281,"passed_time":67.51202249,"remaining_time":4720.574679,"test":[17.99183402]},
{"learn":[0.1063334531],"iteration":282,"passed_time":67.68334843,"remaining_time":4715.592159,"test":[17.9915857]},
{"learn":[0.1039151767],"iteration":283,"passed_time":67.91724927,"remaining_time":4714.987629,"test":[17.99150997]},
{"learn":[0.1016094402],"iteration":284,"passed_time":68.13637037,"remaining_time":4713.363305,"test":[17.99151167]},
{"learn":[0.1005506288],"iteration":285,"passed_time":68.30895821,"remaining_time":4708.541266,"test":[17.99093332]},
{"learn":[0.09955889763],"iteration":286,"passed_time":68.47943725,"remaining_time":4703.606783,"test":[17.99040119]},
{"learn":[0.09866746028],"iteration":287,"passed_time":68.59425474,"remaining_time":4694.895658,"test":[17.99016797]},
{"learn":[0.09691911353],"iteration":288,"passed_time":68.67971468,"remaining_time":4684.241716,"test":[17.99028592]},
{"learn":[0.09585131161],"iteration":289,"passed_time":68.78479336,"remaining_time":4674.994059,"test":[17.9902178]},
{"learn":[0.09356477342],"iteration":290,"passed_time":68.99164844,"remaining_time":4672.702402,"test":[17.99041708]},
{"learn":[0.09093815403],"iteration":291,"passed_time":69.492608,"remaining_time":4690.275063,"test":[17.99031822]},
{"learn":[0.08908215392],"iteration":292,"passed_time":69.74569201,"remaining_time":4691.052397,"test":[17.99057356]},
{"learn":[0.08851726517],"iteration":293,"passed_time":69.87763644,"remaining_time":4683.703074,"test":[17.99034006]},
{"learn":[0.08621322338],"iteration":294,"passed_time":70.05729721,"remaining_time":4679.589972,"test":[17.99036072]},
{"learn":[0.08445772069],"iteration":295,"passed_time":70.25562604,"remaining_time":4676.746133,"test":[17.99015864]},
{"learn":[0.08326355543],"iteration":296,"passed_time":70.44640772,"remaining_time":4673.419432,"test":[17.99012597]},
{"learn":[0.08178820452],"iteration":297,"passed_time":70.69798378,"remaining_time":4674.133142,"test":[17.99013901]},
{"learn":[0.08104117737],"iteration":298,"passed_time":70.82637268,"remaining_time":4666.723639,"test":[17.99002234]},
{"learn":[0.07999815263],"iteration":299,"passed_time":70.9606541,"remaining_time":4659.74962,"test":[17.9900851]},
{"learn":[0.07837577236],"iteration":300,"passed_time":71.18759007,"remaining_time":4658.88484,"test":[17.99024032]},
{"learn":[0.07725803422],"iteration":301,"passed_time":71.34857487,"remaining_time":4653.722609,"test":[17.99024119]},
{"learn":[0.0760549838],"iteration":302,"passed_time":71.53632184,"remaining_time":4650.333106,"test":[17.98992664]},
{"learn":[0.07497006064],"iteration":303,"passed_time":71.67044365,"remaining_time":4643.490323,"test":[17.99022085]},
{"learn":[0.07328608879],"iteration":304,"passed_time":71.94438347,"remaining_time":4645.720106,"test":[17.98998368]},
{"learn":[0.07206125397],"iteration":305,"passed_time":72.08662568,"remaining_time":4639.457537,"test":[17.98982581]},
{"learn":[0.07132652967],"iteration":306,"passed_time":72.26048064,"remaining_time":4635.262688,"test":[17.98983403]},
{"learn":[0.07015515757],"iteration":307,"passed_time":72.41996225,"remaining_time":4630.174989,"test":[17.98977338]},
{"learn":[0.06805394702],"iteration":308,"passed_time":72.7987538,"remaining_time":4639.094696,"test":[17.98975491]},
{"learn":[0.06651010561],"iteration":309,"passed_time":73.01411752,"remaining_time":4637.574109,"test":[17.98976586]},
{"learn":[0.06584384743],"iteration":310,"passed_time":73.18920458,"remaining_time":4633.512055,"test":[17.98986098]},
{"learn":[0.06427704312],"iteration":311,"passed_time":73.39266515,"remaining_time":4631.265357,"test":[17.98955767]},
{"learn":[0.06299918393],"iteration":312,"passed_time":73.56903701,"remaining_time":4627.327897,"test":[17.98937455]},
{"learn":[0.06177075148],"iteration":313,"passed_time":73.70219095,"remaining_time":4620.704876,"test":[17.98925998]},
{"learn":[0.0603831844],"iteration":314,"passed_time":73.87705179,"remaining_time":4616.729411,"test":[17.98952436]},
{"learn":[0.05964229104],"iteration":315,"passed_time":74.02195959,"remaining_time":4610.912192,"test":[17.98954056]},
{"learn":[0.05931551504],"iteration":316,"passed_time":74.07664184,"remaining_time":4599.528521,"test":[17.98958942]},
{"learn":[0.05810545216],"iteration":317,"passed_time":74.3217083,"remaining_time":4599.999568,"test":[17.98955547]},
{"learn":[0.05740589642],"iteration":318,"passed_time":74.45684161,"remaining_time":4593.683698,"test":[17.98952491]},
{"learn":[0.05611921656],"iteration":319,"passed_time":74.6591227,"remaining_time":4591.536046,"test":[17.9894921]},
{"learn":[0.05452527159],"iteration":320,"passed_time":74.89995189,"remaining_time":4591.763717,"test":[17.98921202]},
{"learn":[0.05340630115],"iteration":321,"passed_time":75.1086666,"remaining_time":4590.025905,"test":[17.98907832]},
{"learn":[0.05293574836],"iteration":322,"passed_time":75.26245125,"remaining_time":4584.951248,"test":[17.98902469]},
{"learn":[0.05174744334],"iteration":323,"passed_time":75.47488742,"remaining_time":4583.468781,"test":[17.98895963]},
{"learn":[0.05108194298],"iteration":324,"passed_time":75.65142525,"remaining_time":4579.820898,"test":[17.9888244]},
{"learn":[0.04997716103],"iteration":325,"passed_time":75.80801927,"remaining_time":4574.990709,"test":[17.98867548]},
{"learn":[0.04889370294],"iteration":326,"passed_time":76.0349465,"remaining_time":4574.420497,"test":[17.98870769]},
{"learn":[0.04785508997],"iteration":327,"passed_time":76.19110941,"remaining_time":4569.608245,"test":[17.98875546]},
{"learn":[0.0468341774],"iteration":328,"passed_time":76.35785976,"remaining_time":4565.457323,"test":[17.98869006]},
{"learn":[0.04644467514],"iteration":329,"passed_time":76.50991065,"remaining_time":4560.454371,"test":[17.98873098]},
{"learn":[0.04563970509],"iteration":330,"passed_time":76.74003394,"remaining_time":4560.120023,"test":[17.98866957]},
{"learn":[0.04502223522],"iteration":331,"passed_time":76.87935751,"remaining_time":4554.40724,"test":[17.98860336]},
{"learn":[0.04404680284],"iteration":332,"passed_time":77.06827361,"remaining_time":4551.656868,"test":[17.98851841]},
{"learn":[0.04348144621],"iteration":333,"passed_time":77.20671542,"remaining_time":4545.949896,"test":[17.98832582]},
{"learn":[0.04291482525],"iteration":334,"passed_time":77.39854102,"remaining_time":4543.409878,"test":[17.98825269]},
{"learn":[0.04183076843],"iteration":335,"passed_time":77.58769726,"remaining_time":4540.727616,"test":[17.98811475]},
{"learn":[0.04116970649],"iteration":336,"passed_time":77.7630486,"remaining_time":4537.254672,"test":[17.98802636]},
{"learn":[0.04014057527],"iteration":337,"passed_time":77.94777076,"remaining_time":4534.346357,"test":[17.98780173]},
{"learn":[0.03904637042],"iteration":338,"passed_time":78.19116524,"remaining_time":4534.856932,"test":[17.98777805]},
{"learn":[0.0383552416],"iteration":339,"passed_time":78.36585062,"remaining_time":4531.390068,"test":[17.98779435]},
{"learn":[0.03780237057],"iteration":340,"passed_time":78.57040753,"remaining_time":4529.664638,"test":[17.98776545]},
{"learn":[0.03678217827],"iteration":341,"passed_time":78.79919391,"remaining_time":4529.340801,"test":[17.9877189]},
{"learn":[0.03600553887],"iteration":342,"passed_time":78.90387616,"remaining_time":4521.90523,"test":[17.98775738]},
{"learn":[0.03547194559],"iteration":343,"passed_time":79.03812596,"remaining_time":4516.201755,"test":[17.98764336]},
{"learn":[0.03463954181],"iteration":344,"passed_time":79.30232147,"remaining_time":4517.933706,"test":[17.98766524]},
{"learn":[0.03384663807],"iteration":345,"passed_time":79.44805435,"remaining_time":4512.92503,"test":[17.98757146]},
{"learn":[0.03303484656],"iteration":346,"passed_time":79.66726653,"remaining_time":4512.10602,"test":[17.98750805]},
{"learn":[0.032370876],"iteration":347,"passed_time":79.77462769,"remaining_time":4504.97409,"test":[17.98746295]},
{"learn":[0.03176912313],"iteration":348,"passed_time":79.9336697,"remaining_time":4500.792388,"test":[17.98747766]},
{"learn":[0.03103749994],"iteration":349,"passed_time":80.09730824,"remaining_time":4496.891734,"test":[17.98744085]},
{"learn":[0.03044019034],"iteration":350,"passed_time":80.22706466,"remaining_time":4491.115651,"test":[17.98740802]},
{"learn":[0.03012328078],"iteration":351,"passed_time":80.32498674,"remaining_time":4483.594714,"test":[17.98733866]},
{"learn":[0.02981987325],"iteration":352,"passed_time":80.42547606,"remaining_time":4476.25872,"test":[17.98720784]},
{"learn":[0.02926131863],"iteration":353,"passed_time":80.56707068,"remaining_time":4471.244832,"test":[17.98715105]},
{"learn":[0.02848828539],"iteration":354,"passed_time":80.7820336,"remaining_time":4470.318451,"test":[17.98711263]},
{"learn":[0.02782748823],"iteration":355,"passed_time":81.02843249,"remaining_time":4471.130696,"test":[17.98715762]},
{"learn":[0.02751955184],"iteration":356,"passed_time":81.15037365,"remaining_time":4465.089047,"test":[17.98710215]},
{"learn":[0.02738311775],"iteration":357,"passed_time":81.22403014,"remaining_time":4456.431285,"test":[17.98696187]},
{"learn":[0.02718879771],"iteration":358,"passed_time":81.30523971,"remaining_time":4448.234577,"test":[17.98696326]},
{"learn":[0.02671452809],"iteration":359,"passed_time":81.49710963,"remaining_time":4446.120092,"test":[17.9869669]},
{"learn":[0.02604544524],"iteration":360,"passed_time":81.72977881,"remaining_time":4446.235806,"test":[17.98705194]},
{"learn":[0.02570982931],"iteration":361,"passed_time":81.88401016,"remaining_time":4442.094452,"test":[17.98709736]},
{"learn":[0.02513703263],"iteration":362,"passed_time":82.07805838,"remaining_time":4440.129015,"test":[17.98704049]},
{"learn":[0.02448092921],"iteration":363,"passed_time":82.25672878,"remaining_time":4437.343754,"test":[17.9869418]},
{"learn":[0.02401820062],"iteration":364,"passed_time":82.47831489,"remaining_time":4436.881405,"test":[17.9869353]},
{"learn":[0.02367740037],"iteration":365,"passed_time":82.65605688,"remaining_time":4434.068363,"test":[17.98692201]},
{"learn":[0.02325605583],"iteration":366,"passed_time":82.81999838,"remaining_time":4430.531412,"test":[17.98691019]},
{"learn":[0.02292913277],"iteration":367,"passed_time":82.96671874,"remaining_time":4426.094083,"test":[17.98688972]},
{"learn":[0.02251499709],"iteration":368,"passed_time":83.16449694,"remaining_time":4424.396313,"test":[17.98687273]},
{"learn":[0.02209064385],"iteration":369,"passed_time":83.37038157,"remaining_time":4423.136731,"test":[17.98680533]},
{"learn":[0.02155675646],"iteration":370,"passed_time":83.56411007,"remaining_time":4421.239667,"test":[17.98675013]},
{"learn":[0.0212779113],"iteration":371,"passed_time":83.73614805,"remaining_time":4418.207295,"test":[17.98677396]},
{"learn":[0.02095051427],"iteration":372,"passed_time":83.94110545,"remaining_time":4416.922457,"test":[17.98673876]},
{"learn":[0.02069124825],"iteration":373,"passed_time":84.1324711,"remaining_time":4414.930154,"test":[17.98673596]},
{"learn":[0.02044318758],"iteration":374,"passed_time":84.2754012,"remaining_time":4410.412663,"test":[17.98669224]},
{"learn":[0.02027704353],"iteration":375,"passed_time":84.40000877,"remaining_time":4404.96216,"test":[17.98671113]},
{"learn":[0.01999848577],"iteration":376,"passed_time":84.57434116,"remaining_time":4402.128108,"test":[17.9867269]},
{"learn":[0.01969735581],"iteration":377,"passed_time":84.75051163,"remaining_time":4399.403543,"test":[17.98675247]},
{"learn":[0.01924803884],"iteration":378,"passed_time":84.90924783,"remaining_time":4395.789846,"test":[17.98674102]},
{"learn":[0.01904092569],"iteration":379,"passed_time":85.01188981,"remaining_time":4389.2981,"test":[17.98674751]},
{"learn":[0.01843735079],"iteration":380,"passed_time":85.25927462,"remaining_time":4390.293199,"test":[17.98674827]},
{"learn":[0.01816540451],"iteration":381,"passed_time":85.45151018,"remaining_time":4388.449546,"test":[17.98672945]},
{"learn":[0.0176544608],"iteration":382,"passed_time":85.67516872,"remaining_time":4388.223981,"test":[17.98672882]},
{"learn":[0.01718306368],"iteration":383,"passed_time":85.91613592,"remaining_time":4388.88261,"test":[17.98671541]},
{"learn":[0.01691942644],"iteration":384,"passed_time":86.10559983,"remaining_time":4386.912573,"test":[17.98674806]},
{"learn":[0.01641172625],"iteration":385,"passed_time":86.36664748,"remaining_time":4388.589181,"test":[17.98680435]},
{"learn":[0.01597705169],"iteration":386,"passed_time":86.63565361,"remaining_time":4390.659107,"test":[17.98671932]},
{"learn":[0.0157040985],"iteration":387,"passed_time":86.88367002,"remaining_time":4391.656022,"test":[17.98675182]},
{"learn":[0.01544517177],"iteration":388,"passed_time":87.02762106,"remaining_time":4387.400197,"test":[17.98672708]},
{"learn":[0.01507211765],"iteration":389,"passed_time":87.32934385,"remaining_time":4391.098546,"test":[17.98674158]},
{"learn":[0.01471457005],"iteration":390,"passed_time":87.63155287,"remaining_time":4394.800819,"test":[17.98670177]},
{"learn":[0.01456065635],"iteration":391,"passed_time":87.92714677,"remaining_time":4398.15177,"test":[17.98671041]},
{"learn":[0.01432029093],"iteration":392,"passed_time":88.16431809,"remaining_time":4398.569427,"test":[17.98667895]},
{"learn":[0.01408345238],"iteration":393,"passed_time":88.36830375,"remaining_time":4397.332394,"test":[17.98663861]},
{"learn":[0.01380778382],"iteration":394,"passed_time":88.51278494,"remaining_time":4393.147212,"test":[17.98665688]},
{"learn":[0.01347919887],"iteration":395,"passed_time":88.70660824,"remaining_time":4391.425121,"test":[17.98663207]},
{"learn":[0.01325316121],"iteration":396,"passed_time":88.86359259,"remaining_time":4387.891702,"test":[17.98664267]},
{"learn":[0.01308639786],"iteration":397,"passed_time":88.98803094,"remaining_time":4382.772318,"test":[17.98661223]},
{"learn":[0.01303962408],"iteration":398,"passed_time":89.04713725,"remaining_time":4374.468514,"test":[17.98661099]},
{"learn":[0.01291874068],"iteration":399,"passed_time":89.15524632,"remaining_time":4368.60707,"test":[17.98661836]},
{"learn":[0.01276571927],"iteration":400,"passed_time":89.31843022,"remaining_time":4365.466119,"test":[17.98660013]},
{"learn":[0.01266535765],"iteration":401,"passed_time":89.44814781,"remaining_time":4360.70846,"test":[17.98661094]},
{"learn":[0.01244080126],"iteration":402,"passed_time":89.61752047,"remaining_time":4357.902106,"test":[17.98659741]},
{"learn":[0.01238118819],"iteration":403,"passed_time":89.7814026,"remaining_time":4354.842489,"test":[17.98658069]},
{"learn":[0.0122252247],"iteration":404,"passed_time":89.92781734,"remaining_time":4350.952051,"test":[17.98658633]},
{"learn":[0.01206447874],"iteration":405,"passed_time":90.05531594,"remaining_time":4346.167144,"test":[17.98655377]},
{"learn":[0.01184425909],"iteration":406,"passed_time":90.17737107,"remaining_time":4341.143075,"test":[17.98657413]},
{"learn":[0.01174621457],"iteration":407,"passed_time":90.26910069,"remaining_time":4334.686815,"test":[17.98654491]},
{"learn":[0.01153247011],"iteration":408,"passed_time":90.42708415,"remaining_time":4331.435221,"test":[17.9865028]},
{"learn":[0.01149755839],"iteration":409,"passed_time":90.50797061,"remaining_time":4324.514986,"test":[17.98650066]},
{"learn":[0.011381542],"iteration":410,"passed_time":90.65510611,"remaining_time":4320.785581,"test":[17.98649983]},
{"learn":[0.01114130453],"iteration":411,"passed_time":90.84985018,"remaining_time":4319.337052,"test":[17.98645549]},
{"learn":[0.01102005398],"iteration":412,"passed_time":91.01167126,"remaining_time":4316.333184,"test":[17.98640982]},
{"learn":[0.01077378529],"iteration":413,"passed_time":91.2081494,"remaining_time":4314.982643,"test":[17.98637805]},
{"learn":[0.01060140456],"iteration":414,"passed_time":91.36862313,"remaining_time":4311.938516,"test":[17.98637373]},
{"learn":[0.0104243701],"iteration":415,"passed_time":91.51537544,"remaining_time":4308.26229,"test":[17.98637078]},
{"learn":[0.01022519198],"iteration":416,"passed_time":91.66309864,"remaining_time":4304.648587,"test":[17.98634489]},
{"learn":[0.01008819147],"iteration":417,"passed_time":91.86074358,"remaining_time":4303.390145,"test":[17.98634402]},
{"learn":[0.009864912167],"iteration":418,"passed_time":92.02017154,"remaining_time":4300.350785,"test":[17.98634933]},
{"learn":[0.009660348178],"iteration":419,"passed_time":92.19259525,"remaining_time":4297.930988,"test":[17.98631003]},
{"learn":[0.00946817805],"iteration":420,"passed_time":92.34996304,"remaining_time":4294.821678,"test":[17.98630185]},
{"learn":[0.009252370824],"iteration":421,"passed_time":92.53942784,"remaining_time":4293.215446,"test":[17.98629216]},
{"learn":[0.009056271639],"iteration":422,"passed_time":92.69097746,"remaining_time":4289.861148,"test":[17.98627417]},
{"learn":[0.008870856358],"iteration":423,"passed_time":92.86552679,"remaining_time":4287.58385,"test":[17.98623038]},
{"learn":[0.008821573894],"iteration":424,"passed_time":92.95127843,"remaining_time":4281.22653,"test":[17.98622759]},
{"learn":[0.008774318003],"iteration":425,"passed_time":93.0374644,"remaining_time":4274.918611,"test":[17.98623046]},
{"learn":[0.008638457042],"iteration":426,"passed_time":93.23387536,"remaining_time":4273.692371,"test":[17.98621576]},
{"learn":[0.008539720866],"iteration":427,"passed_time":93.36313726,"remaining_time":4269.400286,"test":[17.98620143]},
{"learn":[0.008393766198],"iteration":428,"passed_time":93.55834039,"remaining_time":4268.13585,"test":[17.98621262]},
{"learn":[0.008348509253],"iteration":429,"passed_time":93.66256534,"remaining_time":4262.735823,"test":[17.98620258]},
{"learn":[0.008095656468],"iteration":430,"passed_time":93.95363332,"remaining_time":4265.843737,"test":[17.9862106]},
{"learn":[0.007905855791],"iteration":431,"passed_time":94.16031106,"remaining_time":4265.113349,"test":[17.98621917]},
{"learn":[0.007784022282],"iteration":432,"passed_time":94.31079365,"remaining_time":4261.845957,"test":[17.98621488]}
]}